semres/__init__.py
semres_jerivas-3.3.0.dist-info/LICENSE
semres_jerivas-3.3.0.dist-info/METADATA
semres_jerivas-3.3.0.dist-info/WHEEL
semres_jerivas-3.3.0.dist-info/top_level.txt
semres_jerivas-3.3.0.dist-info/RECORD
